etldcommonutil/__init__.py
etldcommonutil/pandasglory.py
etldcommonutil/sendemail.py
etldcommonutil-0.1.1.dist-info/LICENSE
etldcommonutil-0.1.1.dist-info/METADATA
etldcommonutil-0.1.1.dist-info/WHEEL
etldcommonutil-0.1.1.dist-info/top_level.txt
etldcommonutil-0.1.1.dist-info/RECORD
