Metadata-Version: 2.1
Name: etldcommonutil
Version: 0.1.1
Summary: In-house common utility
Home-page: https://gitlab.cloud.afterinc.com/DevGroup/bosh/etld_commonutil_package
Author: Rakesh Pandey
Author-email: rpandey@afterinc.com
License: UNKNOWN
Project-URL: Bug Tracker, https://gitlab.cloud.afterinc.com/DevGroup/bosh/etld_commonutil_package/issues
Platform: UNKNOWN
Classifier: Programming Language :: Python :: 3
Classifier: License :: OSI Approved :: MIT License
Classifier: Operating System :: OS Independent
Requires-Python: >=3.6
License-File: LICENSE
